crandr/__init__.py
crandr/__main__.py
crandr/api_swaymsg.py
crandr/api_xrandr.py
crandr/config_paths.py
crandr/connection_parser.py
crandr/main.py
crandr/model.py
crandr/py.typed
crandr/utils.py
crandr/version.py
crandr/doc/.gitignore
crandr/doc/complete.bash
crandr/doc/example_config
crandr-1.6.1.dist-info/entry_points.txt
crandr-1.6.1.dist-info/LICENSE
crandr-1.6.1.dist-info/WHEEL
crandr-1.6.1.dist-info/METADATA
crandr-1.6.1.dist-info/RECORD
