Metadata-Version: 2.3
Name: crandr
Version: 1.6.1
Summary: This is a unifying wrapper around xrandr and swaymsg to control your monitors/outputs,
Author-email: erzo <erzo@posteo.de>
Requires-Python: >=3.8
Classifier: Operating System :: POSIX
Classifier: Operating System :: Unix
Classifier: Environment :: Console
Classifier: License :: OSI Approved :: BSD License
Project-URL: Home, https://gitlab.com/erzo/crandr
